vollseg_napari_mtrack/__init__.py
vollseg_napari_mtrack/_reader.py
vollseg_napari_mtrack/_sample_data.py
vollseg_napari_mtrack/_temporal_plots.py
vollseg_napari_mtrack/_version.py
vollseg_napari_mtrack/_widget.py
vollseg_napari_mtrack/napari.yaml
vollseg_napari_mtrack/_tests/__init__.py
vollseg_napari_mtrack/_tests/test_reader.py
vollseg_napari_mtrack/_tests/test_sample_data.py
vollseg_napari_mtrack/_tests/test_widget.py
vollseg_napari_mtrack/_tests/test_writer.py
vollseg_napari_mtrack/_tests/utils.py
vollseg_napari_mtrack/resources/kapoorlogo.png
vollseg_napari_mtrack-1.4.7.dist-info/LICENSE
vollseg_napari_mtrack-1.4.7.dist-info/METADATA
vollseg_napari_mtrack-1.4.7.dist-info/WHEEL
vollseg_napari_mtrack-1.4.7.dist-info/entry_points.txt
vollseg_napari_mtrack-1.4.7.dist-info/top_level.txt
vollseg_napari_mtrack-1.4.7.dist-info/RECORD
