Metadata-Version: 2.1
Name: vollseg-napari-mtrack
Version: 1.4.7
Summary: Segment kymographs of microtubules, actin filaments and perform Ransac based fits to compute dynamic instability parameters for individual kymographs and also in batch
Home-page: https://github.com/Kapoorlabs-CAPED/vollseg-napari-mtrack
Author: Varun Kapoor
Author-email: randomaccessiblekapoor@gmail.com
License: BSD-3-Clause
Project-URL: Bug Tracker, https://github.com/Kapoorlabs-CAPED/vollseg-napari-mtrack/issues
Project-URL: Documentation, https://github.com/Kapoorlabs-CAPED/vollseg-napari-mtrack#README.md
Project-URL: Source Code, https://github.com/Kapoorlabs-CAPED/vollseg-napari-mtrack
Project-URL: User Support, https://github.com/Kapoorlabs-CAPED/vollseg-napari-mtrack/issues
Classifier: Development Status :: 2 - Pre-Alpha
Classifier: Framework :: napari
Classifier: Intended Audience :: Developers
Classifier: License :: OSI Approved :: BSD License
Classifier: Operating System :: OS Independent
Classifier: Programming Language :: Python
Classifier: Programming Language :: Python :: 3
Classifier: Programming Language :: Python :: 3 :: Only
Classifier: Programming Language :: Python :: 3.8
Classifier: Programming Language :: Python :: 3.9
Classifier: Programming Language :: Python :: 3.10
Classifier: Topic :: Scientific/Engineering :: Image Processing
Requires-Python: >=3.8
License-File: LICENSE
Requires-Dist: numpy
Requires-Dist: magicgui
Requires-Dist: qtpy
Requires-Dist: caped-ai
Provides-Extra: testing
Requires-Dist: tox ; extra == 'testing'
Requires-Dist: pytest ; extra == 'testing'
Requires-Dist: pytest-cov ; extra == 'testing'
Requires-Dist: pytest-qt ; extra == 'testing'
Requires-Dist: napari ; extra == 'testing'
Requires-Dist: pyqt5 ; extra == 'testing'
